pynolist/__init__.py
pynolist-0.0.1.dist-info/LICENSE.txt
pynolist-0.0.1.dist-info/METADATA
pynolist-0.0.1.dist-info/WHEEL
pynolist-0.0.1.dist-info/top_level.txt
pynolist-0.0.1.dist-info/RECORD
