Metadata-Version: 2.1
Name: pynolist
Version: 0.0.1
Summary: List modifying package
Home-page: https://github.com/subhodip00/Pynlist
Author: Subhodip Sinha Choudhury
Author-email: subhodip00@gmail.com
License: UNKNOWN
Platform: UNKNOWN
Classifier: Programming Language :: Python :: 3
Classifier: License :: OSI Approved :: MIT License
Classifier: Operating System :: OS Independent
